python_telegram_auth.py
python_telegram_auth-0.0.1.dist-info/DESCRIPTION.rst
python_telegram_auth-0.0.1.dist-info/METADATA
python_telegram_auth-0.0.1.dist-info/RECORD
python_telegram_auth-0.0.1.dist-info/WHEEL
python_telegram_auth-0.0.1.dist-info/metadata.json
python_telegram_auth-0.0.1.dist-info/top_level.txt
