Metadata-Version: 2.0
Name: python-telegram-auth
Version: 0.0.1
Summary: Implementation of Telegram authorization for websites
Home-page: https://github.com/alxpy/python-telegram-auth
Author: Oleksandr Kuzmenko
Author-email: UNKNOWN
License: MIT
Keywords: python telegram auth login
Platform: UNKNOWN
Classifier: Development Status :: 3 - Alpha
Classifier: Intended Audience :: Developers
Classifier: License :: OSI Approved :: MIT License
Classifier: Programming Language :: Python :: 3
